README.rst
setup.py
ntlmlib/__init__.py
ntlmlib/authentication.py
ntlmlib/constants.py
ntlmlib/context.py
ntlmlib/helpers.py
ntlmlib/messages.py
ntlmlib/security.py
ntlmlib/structure.py
ntlmlib.egg-info/PKG-INFO
ntlmlib.egg-info/SOURCES.txt
ntlmlib.egg-info/dependency_links.txt
ntlmlib.egg-info/requires.txt
ntlmlib.egg-info/top_level.txt