Metadata-Version: 1.1
Name: ntlmlib
Version: 0.72
Summary: A robust, fast and efficient first-class Python library for NTLMv1 and NTLMv2 authentication with signing and encryption
Home-page: http://github.com/ianclegg/ntlmlib/
Author: Ian Clegg
Author-email: ian.clegg@sourcewarp.com
License: Apache 2.0
Keywords: ntlm,ntlmv2,gss,gssapi,sign,seal,authentication
Platform: UNKNOWN
Classifier: Development Status :: 3 - Alpha
Classifier: Environment :: Console
Classifier: Intended Audience :: Developers
Classifier: Natural Language :: English
Classifier: License :: OSI Approved :: Apache Software License
Classifier: Programming Language :: Python
Classifier: Programming Language :: Python :: 2
Classifier: Programming Language :: Python :: 2.6
Classifier: Programming Language :: Python :: 2.7
Classifier: Programming Language :: Python :: 3
Classifier: Programming Language :: Python :: 3.2
Classifier: Programming Language :: Python :: 3.3
Classifier: Programming Language :: Python :: 3.4
Classifier: Programming Language :: Python :: 3.5
Classifier: Programming Language :: Python :: Implementation :: PyPy
Classifier: Topic :: Software Development :: Libraries :: Python Modules
